<annotation>
	<folder>Organik</folder>
	<filename>IMG (1120).jpg</filename>
	<path>C:\Users\ASUS\Documents\KULIAH\SIB\CAPSTONE\DATASET\TRAIN\Organik\O_1436.jpg</path>
	<source>
		<database>Unknown</database>
	</source>
	<size>
		<width>220</width>
		<height>229</height>
		<depth>3</depth>
	</size>
	<segmented>0</segmented>
	<object>
		<name>Organik</name>
		<pose>Unspecified</pose>
		<truncated>0</truncated>
		<difficult>0</difficult>
		<bndbox>
			<xmin>11</xmin>
			<ymin>17</ymin>
			<xmax>205</xmax>
			<ymax>180</ymax>
		</bndbox>
	</object>
</annotation>