<annotation>
	<folder>Organik</folder>
	<filename>IMG (1041).jpg</filename>
	<path>C:\Users\ASUS\Documents\KULIAH\SIB\CAPSTONE\DATASET\TRAIN\Organik\O_107.jpg</path>
	<source>
		<database>Unknown</database>
	</source>
	<size>
		<width>193</width>
		<height>261</height>
		<depth>3</depth>
	</size>
	<segmented>0</segmented>
	<object>
		<name>Organik</name>
		<pose>Unspecified</pose>
		<truncated>0</truncated>
		<difficult>0</difficult>
		<bndbox>
			<xmin>6</xmin>
			<ymin>2</ymin>
			<xmax>186</xmax>
			<ymax>253</ymax>
		</bndbox>
	</object>
</annotation>