<annotation>
	<folder>Rec_Paper</folder>
	<filename>paper-17.jpg</filename>
	<path>C:\Users\ASUS\Documents\KULIAH\SIB\CAPSTONE\DATASET\TRAIN\Rec_Paper\paper-17.jpg</path>
	<source>
		<database>Unknown</database>
	</source>
	<size>
		<width>800</width>
		<height>800</height>
		<depth>3</depth>
	</size>
	<segmented>0</segmented>
	<object>
		<name>Rec_Paper</name>
		<pose>Unspecified</pose>
		<truncated>0</truncated>
		<difficult>0</difficult>
		<bndbox>
			<xmin>94</xmin>
			<ymin>139</ymin>
			<xmax>676</xmax>
			<ymax>678</ymax>
		</bndbox>
	</object>
</annotation>
